setup.py
http_api_exception/__init__.py
http_api_exception/_base.py
http_api_exception/flask_errors.py
http_api_exception.egg-info/PKG-INFO
http_api_exception.egg-info/SOURCES.txt
http_api_exception.egg-info/dependency_links.txt
http_api_exception.egg-info/not-zip-safe
http_api_exception.egg-info/requires.txt
http_api_exception.egg-info/top_level.txt