Metadata-Version: 2.1
Name: http-api-exception
Version: 0.0.2
Summary: Python Common Api Exceptions for HTTP-JSON-Response
Home-page: https://github.com/dodoru/pyco-api-exceptions
Author: Nico Ning
Author-email: dodoru@foxmail.com
License: MIT
Platform: any
Classifier: License :: OSI Approved :: MIT License
Classifier: Operating System :: OS Independent
Classifier: Programming Language :: Python
Classifier: Programming Language :: Python :: 3.4
Classifier: Programming Language :: Python :: 3.5
Classifier: Programming Language :: Python :: 3.6
Classifier: Programming Language :: Python :: 3.7
Classifier: Programming Language :: Python :: 3.8
Classifier: Programming Language :: Python :: 3.9
Classifier: Topic :: Utilities
Classifier: Development Status :: 4 - Beta
